[
  {
    "arabic": " سُبْحَانَ اللَّهِ وَبِحَمْدِهِ، سُبْحَانَ اللَّهِ العَظِيم",
    "english": "Subhanallahi Wa Bihamdihi Subhanallahil Azeem",
    "times": 0
  },
  {
    "arabic": "لَا إِلَٰهَ إِلَّا ٱللَّٰهُ مُحَمَّدٌ رَسُولُ ٱللَّٰهِ",
    "english": "La ilaha illallahu muhammadur rasulullah",
    "times": 0
  },
  {
    "arabic": "اَشْهَدُ اَنْ لَّآ اِلٰهَ اِلَّا اللهُ وَحْدَہٗ لَاشَرِيْكَ لَہٗ وَاَشْهَدُ اَنَّ مُحَمَّدًا عَبْدُهٗ وَرَسُولُہٗ",
    "english": "Ashhadu al-La Ilaha Ila Allah, Wa Ashhadu an-na Muhammadan Abduhu wa Rasuluhu",
    "times": 0
  },
  {
    "arabic": "سُبْحَان اللهِ وَالْحَمْدُلِلّهِ وَلا إِلهَ إِلّااللّهُ وَاللّهُ أكْبَرُ وَلا حَوْلَ وَلاَ قُوَّةَ إِلَّا بِاللّهِ الْعَلِيِّ الْعَظِيْم",
    "english": "Subhana Allah, wa Al-hamdu li Allah, wa la Ilaha Ila Allah, wa Allahu Akbar, wa la hawla wa la Quata ila bi-Allahi al-Alai al-Azeem",
    "times": 0
  },
  {
    "arabic": "لَآ اِلٰهَ اِلَّا اللهُ وَحْدَهٗ لَا شَرِيْكَ لَهٗ لَهُ الْمُلْكُ وَ لَهُ الْحَمْدُ يُحْىٖ وَ يُمِيْتُ وَ هُوَحَیٌّ لَّا يَمُوْتُ اَبَدًا اَبَدًاؕ ذُو الْجَلَالِ وَالْاِكْرَامِؕ بِيَدِهِ الْخَيْرُؕ وَهُوَ عَلٰى كُلِّ شیْ ٍٔ قَدِیْرٌؕ",
    "english": "Lā ilāha illallāh waḥdahu lā sharīka lah, Lahu ‘l-mulku wa lahu ‘l-ḥamd, Yuḥyī wa yumīt, Biyadihi ‘l-khayr, wa huwa `alā kulli shay’in Qadīr.",
    "times": 0
  },
  {
    "arabic": "اَسْتَغْفِرُ اللهِ رَبِّىْ مِنْ كُلِِّ ذَنْۢبٍ اَذْنَبْتُهٗ عَمَدًا اَوْ خَطَا ًٔ سِرًّا اَوْ عَلَانِيَةً وَّاَتُوْبُ اِلَيْهِ مِنَ الذَّنْۢبِ الَّذِیْٓ اَعْلَمُ وَ مِنَ الذَّنْۢبِ الَّذِىْ لَآ اَعْلَمُ اِنَّكَ اَنْتَ عَلَّامُ الْغُيُوْبِ وَ سَتَّارُ الْعُيُوْبِ و َغَفَّارُ الذُّنُوْبِ وَ لَا حَوْلَ وَلَا قُوَّةَ اِلَّا بِاللهِ الْعَلِىِِّ الْعَظِيْمِؕ",
    "english": "Istaghfiru Allah Rabi min kuli dhanbin adhnabtuh, a’w khatai’n siran a’w ‘alanatin, wa atoob ilaihi min adh-anbi al-ladhi a’lam, wa min adh-anbi al-ladhi la a’lam, Inaka Anta Alaam al-ghuyoob, wa Sattaar al-‘uyoob, wa ghfaar al-dhunoob, wa la hawla wa la quwata ila bi Allahi al-Alai al-Azeem",
    "times": 0
  },
  {
    "arabic": "اَللّٰهُمَّ اِنِّیْٓ اَعُوْذُ بِكَ مِنْ اَنْ اُشْرِكَ بِكَ شَيْئًا وَّاَنَآ اَعْلَمُ بِهٖ وَ اَسْتَغْفِرُكَ لِمَا لَآ اَعْلَمُ بِهٖ تُبْتُ عَنْهُ وَ تَبَرَّأْتُ مِنَ الْكُفْرِ وَ الشِّرْكِ وَ الْكِذْبِ وَ الْغِيْبَةِ وَ الْبِدْعَةِ وَ النَّمِيْمَةِ وَ الْفَوَاحِشِ وَ الْبُهْتَانِ وَ الْمَعَاصِىْ كُلِِّهَا وَ اَسْلَمْتُ وَ اَقُوْلُ لَآ اِلٰهَ اِلَّا اللهُ مُحَمَّدٌ رَّسُوْلُ اللهِؕ",
    "english": "Allahuma Ini a’uthu bika min an ushrika bika shi’an wa ana a’lamu bih, wa astaghfiruka lima la a’lamu bih, tubtu anhu, wa tabar’tu min al-kufri wa ash-shirki wa al-kazibi wa al-ma’asy kulaha. Aslamtu wa ‘aamantu wa aquul: la ilaha ila Allah, Muhammad rasulu Allah",
    "times": 0
  }
]
